url_for_s3.py
url_for_s3-0.1.2.dist-info/RECORD
url_for_s3-0.1.2.dist-info/DESCRIPTION.rst
url_for_s3-0.1.2.dist-info/top_level.txt
url_for_s3-0.1.2.dist-info/METADATA
url_for_s3-0.1.2.dist-info/WHEEL
url_for_s3-0.1.2.dist-info/metadata.json
