Metadata-Version: 2.0
Name: url-for-s3
Version: 0.1.2
Summary: Python function that generates a URL to a given S3 resource.
Home-page: https://github.com/Jaza/url-for-s3
Author: Jeremy Epstein
Author-email: jazepstein@gmail.com
License: UNKNOWN
Platform: any
Classifier: Development Status :: 2 - Pre-Alpha
Classifier: Environment :: Web Environment
Classifier: Intended Audience :: Developers
Classifier: Operating System :: OS Independent
Classifier: Programming Language :: Python
Classifier: Programming Language :: Python :: 2
Classifier: Programming Language :: Python :: 2.7
Classifier: Programming Language :: Python :: 3
Classifier: Programming Language :: Python :: 3.3
